paleo/__init__.py
paleo/constants.py
paleo/graph_edits.py
paleo/io.py
paleo/level2_graph.py
paleo/networkdelta.py
paleo/replay.py
paleo/skeletons.py
paleo/synapses.py
paleo/types.py
paleo/utils.py
paleo-0.4.0.dist-info/METADATA
paleo-0.4.0.dist-info/WHEEL
paleo-0.4.0.dist-info/licenses/LICENSE
paleo-0.4.0.dist-info/RECORD
